[{"item": "factory_1", "properties": ["moto", "powered"], "sha1": "0f:ac:6f:7d:5e:e0:40:e9:7f:9b:35:2c:0d:68:52:5b:fb:ba:9f:0a", "size": 18}, {"item": "compressor_28", "properties": ["manual", "startup_t"], "sha1": "d8:1f:7a:07:28:e1:ce:4b:0a:43:21:db:2a:2a:08:4d:30:c5:e4:2d", "size": 11}, {"item": "motor_1", "properties": ["manual", "startup_t", "sp"], "sha1": "0b:d0:be:fe:a1:07:95:a8:f9:c6:dd:4d:eb:c7:eb:18:6a:3b:a7:c0", "size": 20}, {"item": "motor_2", "properties": ["manual", "startup_t"], "sha1": "d8:1f:7a:07:28:e1:ce:4b:0a:43:21:db:2a:2a:08:4d:30:c5:e4:2d", "size": 11}, {"item": "motor_4", "properties": ["manual", "startup_t"], "sha1": "d8:1f:7a:07:28:e1:ce:4b:0a:43:21:db:2a:2a:08:4d:30:c5:e4:2d", "size": 11}, {"item": "motor_6", "properties": ["manual", "startup_t"], "sha1": "d8:1f:7a:07:28:e1:ce:4b:0a:43:21:db:2a:2a:08:4d:30:c5:e4:2d", "size": 11}]